turk_web_kaziyici/__init__.py
turk_web_kaziyici/__main__.py
turk_web_kaziyici/cli.py
turk_web_kaziyici/config.py
turk_web_kaziyici/models.py
turk_web_kaziyici/scraper.py
turk_web_kaziyici/utils.py
turk_web_kaziyici-0.1.0.dist-info/licenses/LICENCE
turk_web_kaziyici-0.1.0.dist-info/METADATA
turk_web_kaziyici-0.1.0.dist-info/WHEEL
turk_web_kaziyici-0.1.0.dist-info/top_level.txt
turk_web_kaziyici-0.1.0.dist-info/RECORD
