Metadata-Version: 2.4
Name: turk-web-kaziyici
Version: 0.1.0
License-File: LICENCE
Requires-Dist: requests
Requires-Dist: beautifulsoup4
Requires-Dist: pytest
Dynamic: license-file
